datatoolkit/__init__.py
datatoolkit/hypothesis.py
datatoolkit/mock_dataset.py
datatoolkit/model_selection.py
datatoolkit/utils.py
datatoolkit/visualize.py
datatoolkit-0.2.5.dist-info/METADATA
datatoolkit-0.2.5.dist-info/WHEEL
datatoolkit-0.2.5.dist-info/LICENSE
datatoolkit-0.2.5.dist-info/RECORD
