Metadata-Version: 2.1
Name: datatoolkit
Version: 0.2.5
Summary: A collection of tools for visualization and data processing for exploratory data analysis
License: MIT
Author: Humberto STEIN SHIROMOTO
Author-email: h.stein.shiromoto@gmail.com
Requires-Python: >=3.9,<4
Classifier: License :: OSI Approved :: MIT License
Classifier: Programming Language :: Python :: 3
Classifier: Programming Language :: Python :: 3.9
Classifier: Programming Language :: Python :: 3.10
Classifier: Programming Language :: Python :: 3.11
Requires-Dist: bokeh (>=2.4.0,<3.0.0)
Requires-Dist: hyperopt (>=0.2.7,<0.3.0)
Requires-Dist: networkx (>=2.6.3,<3.0.0)
Requires-Dist: scikit-learn (>=1.2.0,<2.0.0)
Requires-Dist: seaborn (>=0.11.2,<0.12.0)
Requires-Dist: statsmodels (>=0.13.0,<0.14.0)
Requires-Dist: typeguard (>=2.12.1,<3.0.0)
